cflabs/__init__.py
cflabs/client.py
cflabs-0.1.5.dist-info/METADATA
cflabs-0.1.5.dist-info/WHEEL
cflabs-0.1.5.dist-info/licenses/LICENSE
cflabs-0.1.5.dist-info/RECORD
