Metadata-Version: 2.4
Name: cflabs
Version: 0.1.5
Summary: CFLabs Python SDK
Project-URL: Homepage, https://github.com/chainforge-ai/sdk_octavian
Project-URL: Repository, https://github.com/chainforge-ai/sdk_octavian
Project-URL: Documentation, https://github.com/chainforge-ai/sdk_octavian#readme
Project-URL: Issues, https://github.com/chainforge-ai/sdk_octavian/issues
Author-email: CFLabs <info@cflabs.com>
License: MIT License
License-File: LICENSE
Keywords: api,cflabs,sdk
Classifier: Development Status :: 3 - Alpha
Classifier: Intended Audience :: Developers
Classifier: License :: OSI Approved :: MIT License
Classifier: Programming Language :: Python :: 3
Classifier: Programming Language :: Python :: 3.8
Classifier: Programming Language :: Python :: 3.9
Classifier: Programming Language :: Python :: 3.10
Classifier: Programming Language :: Python :: 3.11
Classifier: Programming Language :: Python :: 3.12
Requires-Python: >=3.8
Requires-Dist: requests>=2.31.0
